<treballadors>
	<treballador>
		<nom>Xavi</nom>
		<cognoms>Barriendos</cognoms>
		<data_naixement>1999-04-02</data_naixement>
		<antiguitat>5</antiguitat>
		<codi_rol>1</codi_rol>
	</treballador>
	<treballador>
		<nom>Pegfsdfge</nom>
		<cognoms>Linares</cognoms>
		<data_naixement>2000-12-29</data_naixement>
		<antiguitat>2</antiguitat>
		<codi_rol>1</codi_rol>
	</treballador>
    	<treballador>
		<nom>Xasfdgsvi</nom>
		<cognoms>Barriendos</cognoms>
		<data_naixement>1999-04-02</data_naixement>
		<antiguitat>5</antiguitat>
		<codi_rol>1</codi_rol>
	</treballador>
	<treballador>
		<nom>Pesdfgre</nom>
		<cognoms>Linares</cognoms>
		<data_naixement>2000-12-29</data_naixement>
		<antiguitat>2</antiguitat>
		<codi_rol>1</codi_rol>
	</treballador>
    	<treballador>
		<nom>Xasfdgraevi</nom>
		<cognoms>Barraregiendos</cognoms>
		<data_naixement>1999-04-02</data_naixement>
		<antiguitat>5</antiguitat>
		<codi_rol>1</codi_rol>
	</treballador>
</treballadors>